mineflex/__init__.py
mineflex/auth.py
mineflex/endpoint.py
mineflex/exceptions.py
mineflex/player.py
mineflex/server.py
mineflex_py-1.0.3.dist-info/LICENSE
mineflex_py-1.0.3.dist-info/METADATA
mineflex_py-1.0.3.dist-info/WHEEL
mineflex_py-1.0.3.dist-info/top_level.txt
mineflex_py-1.0.3.dist-info/RECORD
